{
  "/_global-error/page": "app/_global-error/page.js",
  "/_not-found/page": "app/_not-found/page.js",
  "/admin/[[...path]]/page": "app/admin/[[...path]]/page.js",
  "/admin/login/page": "app/admin/login/page.js",
  "/api/admin/admin-emails/[id]/route": "app/api/admin/admin-emails/[id]/route.js",
  "/api/admin/admin-emails/route": "app/api/admin/admin-emails/route.js",
  "/api/admin/admin-users/[id]/route": "app/api/admin/admin-users/[id]/route.js",
  "/api/admin/admin-users/route": "app/api/admin/admin-users/route.js",
  "/api/admin/categories/[id]/route": "app/api/admin/categories/[id]/route.js",
  "/api/admin/categories/route": "app/api/admin/categories/route.js",
  "/api/admin/dashboard-stats/route": "app/api/admin/dashboard-stats/route.js",
  "/api/admin/hero-images/route": "app/api/admin/hero-images/route.js",
  "/api/admin/imgbb-upload/route": "app/api/admin/imgbb-upload/route.js",
  "/api/admin/login/route": "app/api/admin/login/route.js",
  "/api/admin/product-images/route": "app/api/admin/product-images/route.js",
  "/api/admin/products/[id]/route": "app/api/admin/products/[id]/route.js",
  "/api/admin/products/route": "app/api/admin/products/route.js",
  "/api/admin/site-settings/route": "app/api/admin/site-settings/route.js",
  "/api/admin/social-gallery/[id]/route": "app/api/admin/social-gallery/[id]/route.js",
  "/api/admin/social-gallery/route": "app/api/admin/social-gallery/route.js",
  "/api/admin/testimonials/[id]/route": "app/api/admin/testimonials/[id]/route.js",
  "/api/admin/testimonials/route": "app/api/admin/testimonials/route.js",
  "/api/catalog/route": "app/api/catalog/route.js",
  "/api/popular/route": "app/api/popular/route.js",
  "/api/site-settings/route": "app/api/site-settings/route.js",
  "/api/social-gallery/route": "app/api/social-gallery/route.js",
  "/api/testimonials/route": "app/api/testimonials/route.js",
  "/page": "app/page.js",
  "/robots.txt/route": "app/robots.txt/route.js",
  "/sitemap.xml/route": "app/sitemap.xml/route.js"
}